rabbitfixture/__init__.py
rabbitfixture/server.py
rabbitfixture/tests/__init__.py
rabbitfixture/tests/test_server.py
rabbitfixture-0.5.4.dist-info/LICENSE
rabbitfixture-0.5.4.dist-info/METADATA
rabbitfixture-0.5.4.dist-info/WHEEL
rabbitfixture-0.5.4.dist-info/top_level.txt
rabbitfixture-0.5.4.dist-info/RECORD
