Metadata-Version: 2.1
Name: rabbitfixture
Version: 0.5.4
Summary: A RabbitMQ fixture.
Home-page: https://launchpad.net/rabbitfixture
Author: Launchpad developers
Maintainer: Launchpad developers
License: AGPL-3.0-only
Project-URL: Source, https://code.launchpad.net/rabbitfixture
Project-URL: Issue Tracker, https://bugs.launchpad.net/rabbitfixture
Classifier: Development Status :: 5 - Production/Stable
Classifier: Intended Audience :: Developers
Classifier: License :: OSI Approved :: GNU Affero General Public License v3
Classifier: Operating System :: OS Independent
Classifier: Programming Language :: Python
Classifier: Programming Language :: Python :: 2
Classifier: Programming Language :: Python :: 2.7
Classifier: Programming Language :: Python :: 3
Classifier: Programming Language :: Python :: 3.4
Classifier: Programming Language :: Python :: 3.5
Classifier: Programming Language :: Python :: 3.6
Classifier: Programming Language :: Python :: 3.7
Requires-Python: >=2.7, !=3.0.*, !=3.1.*, !=3.2.*, !=3.3.*, <3.8
License-File: LICENSE
Requires-Dist: amqp >=2.0.0
Requires-Dist: fixtures >=0.3.6
Requires-Dist: setuptools
Requires-Dist: testtools >=0.9.12
Requires-Dist: subprocess32 ; python_version < "3"
Provides-Extra: test
Requires-Dist: six ; extra == 'test'
